deeplense_domain_adaptation/__init__.py
deeplense_domain_adaptation/algorithms/__init__.py
deeplense_domain_adaptation/algorithms/adamatch.py
deeplense_domain_adaptation/algorithms/adda.py
deeplense_domain_adaptation/algorithms/cgdm.py
deeplense_domain_adaptation/algorithms/self_ensemble.py
deeplense_domain_adaptation/algorithms/supervised.py
deeplense_domain_adaptation/data/__init__.py
deeplense_domain_adaptation/data/augmentations.py
deeplense_domain_adaptation/data/dataset.py
deeplense_domain_adaptation/data/hyperparams.py
deeplense_domain_adaptation/networks/__init__.py
deeplense_domain_adaptation/networks/discriminator.py
deeplense_domain_adaptation/networks/equivariant.py
deeplense_domain_adaptation/networks/resnet.py
deeplense_domain_adaptation-1.0.0.dist-info/LICENSE
deeplense_domain_adaptation-1.0.0.dist-info/METADATA
deeplense_domain_adaptation-1.0.0.dist-info/WHEEL
deeplense_domain_adaptation-1.0.0.dist-info/top_level.txt
deeplense_domain_adaptation-1.0.0.dist-info/RECORD
